LICENSE.txt
README.rst
pgperf/__init__.py
pgperf/db.py
pgperf/docs/index.md
pgperf/docs/pgperf/main.md
pgperf/index/__init__.py
pgperf/index/main.py
pgperf/main.py
pgperf/mkdocs.yml
pgperf/mkgendocs.yml
pgperf/server/__init__.py
pgperf/server/additional/__init__.py
pgperf/server/configuration/__init__.py
pgperf/server/configuration/replication.py
pgperf/server/main.py
pgperf/server/stats/__init__.py
pgperf/server/stats/collected.py
pgperf/server/stats/dinamic.py
pgperf/site/404.html
pgperf/site/css/fonts/Roboto-Slab-Bold.woff
pgperf/site/css/fonts/Roboto-Slab-Bold.woff2
pgperf/site/css/fonts/Roboto-Slab-Regular.woff
pgperf/site/css/fonts/Roboto-Slab-Regular.woff2
pgperf/site/css/fonts/fontawesome-webfont.eot
pgperf/site/css/fonts/fontawesome-webfont.svg
pgperf/site/css/fonts/fontawesome-webfont.ttf
pgperf/site/css/fonts/fontawesome-webfont.woff
pgperf/site/css/fonts/fontawesome-webfont.woff2
pgperf/site/css/fonts/lato-bold-italic.woff
pgperf/site/css/fonts/lato-bold-italic.woff2
pgperf/site/css/fonts/lato-bold.woff
pgperf/site/css/fonts/lato-bold.woff2
pgperf/site/css/fonts/lato-normal-italic.woff
pgperf/site/css/fonts/lato-normal-italic.woff2
pgperf/site/css/fonts/lato-normal.woff
pgperf/site/css/fonts/lato-normal.woff2
pgperf/site/css/theme.css
pgperf/site/css/theme_extra.css
pgperf/site/img/favicon.ico
pgperf/site/index.html
pgperf/site/js/html5shiv.min.js
pgperf/site/js/jquery-3.6.0.min.js
pgperf/site/js/theme.js
pgperf/site/js/theme_extra.js
pgperf/site/pgperf/main/index.html
pgperf/site/search/lunr.js
pgperf/site/search/main.js
pgperf/site/search/search_index.json
pgperf/site/search/worker.js
pgperf/site/search.html
pgperf/site/sitemap.xml
pgperf/site/sitemap.xml.gz
pgperf/table/__init__.py
pgperf/table/main.py
pgperf/templates/all_locks.sql
pgperf/templates/bloat.sql
pgperf/templates/blocking.sql
pgperf/templates/buffercache_stats.sql
pgperf/templates/buffercache_usage.sql
pgperf/templates/cache_hit.sql
pgperf/templates/calls.sql
pgperf-1.0.1.dist-info/LICENSE.txt
pgperf-1.0.1.dist-info/METADATA
pgperf-1.0.1.dist-info/WHEEL
pgperf-1.0.1.dist-info/entry_points.txt
pgperf-1.0.1.dist-info/RECORD
