Metadata-Version: 2.1
Name: pgperf
Version: 1.0.1
Summary: PostgreSQL Performance Tools
Home-page: https://github.com/aldovillagra/pgperf
License: GPL-3.0-or-later
Author: Aldo A. Villagra B.
Author-email: aldovillagra@gmail.com
Requires-Python: >=3.8,<4.0
Classifier: License :: OSI Approved :: GNU General Public License v3 or later (GPLv3+)
Classifier: Programming Language :: Python :: 3
Classifier: Programming Language :: Python :: 3.8
Classifier: Programming Language :: Python :: 3.9
Classifier: Programming Language :: Python :: 3.10
Classifier: Programming Language :: Python :: 3.11
Requires-Dist: Jinja2 (>=3.1.2,<4.0.0)
Requires-Dist: SQLAlchemy (>=1.4.36,<2.0.0)
Requires-Dist: XlsxWriter (>=3.0.3,<4.0.0)
Requires-Dist: numpy (>=1.22.4,<2.0.0)
Requires-Dist: omegaconf (>=2.2.1,<3.0.0)
Requires-Dist: pandas (>=1.4.2,<2.0.0)
Requires-Dist: psycopg2 (>=2.9.3,<3.0.0)
Requires-Dist: tabulate (>=0.8.9,<0.9.0)
Requires-Dist: typer[all] (>=0.9.0,<0.10.0)
Project-URL: Bug Tracker, https://github.com/aldovillagra/pgperf/issues
Project-URL: Documentation, https://github.com/aldovillagra/pgperf#readme
Project-URL: Repository, https://github.com/aldovillagra/pgperf
